modelbaker/__init__.py
modelbaker/dataobjects/__init__.py
modelbaker/dataobjects/fields.py
modelbaker/dataobjects/form.py
modelbaker/dataobjects/layers.py
modelbaker/dataobjects/legend.py
modelbaker/dataobjects/project.py
modelbaker/dataobjects/relations.py
modelbaker/db_factory/__init__.py
modelbaker/db_factory/db_command_config_manager.py
modelbaker/db_factory/db_factory.py
modelbaker/db_factory/db_simple_factory.py
modelbaker/db_factory/gpkg_command_config_manager.py
modelbaker/db_factory/gpkg_factory.py
modelbaker/db_factory/gpkg_layer_uri.py
modelbaker/db_factory/layer_uri.py
modelbaker/db_factory/mssql_command_config_manager.py
modelbaker/db_factory/mssql_factory.py
modelbaker/db_factory/mssql_layer_uri.py
modelbaker/db_factory/pg_command_config_manager.py
modelbaker/db_factory/pg_factory.py
modelbaker/db_factory/pg_layer_uri.py
modelbaker/dbconnector/__init__.py
modelbaker/dbconnector/config.py
modelbaker/dbconnector/db_connector.py
modelbaker/dbconnector/gpkg_connector.py
modelbaker/dbconnector/mssql_connector.py
modelbaker/dbconnector/pg_connector.py
modelbaker/generator/__init__.py
modelbaker/generator/config.py
modelbaker/generator/domain_relations_generator.py
modelbaker/generator/generator.py
modelbaker/ilitoppingmaker/__init__.py
modelbaker/ilitoppingmaker/ili2dbsettings.py
modelbaker/ilitoppingmaker/ilidata.py
modelbaker/ilitoppingmaker/iliprojecttopping.py
modelbaker/ilitoppingmaker/ilitarget.py
modelbaker/ilitoppingmaker/metaconfig.py
modelbaker/iliwrapper/__init__.py
modelbaker/iliwrapper/globals.py
modelbaker/iliwrapper/ili2dbargs.py
modelbaker/iliwrapper/ili2dbconfig.py
modelbaker/iliwrapper/ili2dbtools.py
modelbaker/iliwrapper/ili2dbutils.py
modelbaker/iliwrapper/ilicache.py
modelbaker/iliwrapper/ilideleter.py
modelbaker/iliwrapper/iliexecutable.py
modelbaker/iliwrapper/iliexporter.py
modelbaker/iliwrapper/iliimporter.py
modelbaker/iliwrapper/ilimetaconfigexporter.py
modelbaker/iliwrapper/iliupdater.py
modelbaker/iliwrapper/ilivalidator.py
modelbaker-2.4.2.dist-info/licenses/LICENSE
modelbaker-2.4.2.dist-info/METADATA
modelbaker-2.4.2.dist-info/WHEEL
modelbaker-2.4.2.dist-info/top_level.txt
modelbaker-2.4.2.dist-info/RECORD
