Metadata-Version: 2.4
Name: modelbaker
Version: 2.4.2
Summary: The full model baker core
Home-page: https://github.com/opengisch/QgisModelBakerLibrary
Author: Dave Signer
Author-email: david@opengis.ch
Classifier: Topic :: Database
Classifier: License :: OSI Approved :: GNU General Public License v2 or later (GPLv2+)
Classifier: Programming Language :: Python :: 3
Classifier: License :: OSI Approved :: MIT License
Classifier: Operating System :: OS Independent
Requires-Python: >=3.7
License-File: LICENSE
Dynamic: author
Dynamic: author-email
Dynamic: classifier
Dynamic: description
Dynamic: description-content-type
Dynamic: home-page
Dynamic: license-file
Dynamic: requires-python
Dynamic: summary
